dnv/__init__.py
dnv/f2at_helpers/__init__.py
dnv/f2at_helpers/example.py
dnv/f2at_helpers/f2at_helpers.py
dnv_f2at_helpers-0.1.4.dist-info/LICENSE
dnv_f2at_helpers-0.1.4.dist-info/METADATA
dnv_f2at_helpers-0.1.4.dist-info/WHEEL
dnv_f2at_helpers-0.1.4.dist-info/top_level.txt
dnv_f2at_helpers-0.1.4.dist-info/RECORD
