Metadata-Version: 2.1
Name: dnv-f2at-helpers
Version: 0.1.4
Summary: Python library for running F²AT calculations and soil spring calibrations on the OneCompute cloud platform.
Author-email: DNV AS <software.support@dnv.com>
License: MIT License
Project-URL: Homepage, https://myworkspace-dev.dnv.com/download/sesam/Infidep/downloads/docs/index.html
Keywords: f2at,infidep,splice,sesam,onecompute,dnv,ngi
Classifier: License :: OSI Approved :: MIT License
Classifier: Programming Language :: Python
Classifier: Programming Language :: Python :: 3.10
Requires-Python: >=3.10
License-File: LICENSE
Requires-Dist: dnv-onecompute>=10.0.0
Requires-Dist: dnv-sesam-commands>=5.22.0
